Metadata-Version: 2.4
Name: amplify-excel-migrator
Version: 1.3.2
Summary: A CLI tool to migrate Excel data to AWS Amplify
Home-page: https://github.com/EyalPoly/amplify-excel-migrator
Author: Eyal Politansky
Author-email: 10eyal10@gmail.com
Classifier: Programming Language :: Python :: 3
Classifier: License :: OSI Approved :: MIT License
Classifier: Operating System :: OS Independent
Requires-Python: >=3.8
License-File: LICENSE
Requires-Dist: pandas>=1.3.0
Requires-Dist: requests>=2.26.0
Requires-Dist: boto3>=1.18.0
Requires-Dist: pycognito>=2023.5.0
Requires-Dist: PyJWT>=2.0.0
Requires-Dist: aiohttp>=3.8.0
Requires-Dist: openpyxl>=3.0.0
Requires-Dist: inflect>=7.0.0
Provides-Extra: dev
Requires-Dist: pytest>=8.0.0; extra == "dev"
Requires-Dist: pytest-cov>=4.1.0; extra == "dev"
Requires-Dist: pytest-mock>=3.12.0; extra == "dev"
Requires-Dist: pytest-asyncio>=0.21.0; extra == "dev"
Requires-Dist: setuptools>=80.0.0; extra == "dev"
Requires-Dist: wheel>=0.40.0; extra == "dev"
Requires-Dist: twine>=4.0.0; extra == "dev"
Dynamic: author
Dynamic: author-email
Dynamic: classifier
Dynamic: description
Dynamic: description-content-type
Dynamic: home-page
Dynamic: license-file
Dynamic: provides-extra
Dynamic: requires-dist
Dynamic: requires-python
Dynamic: summary
